LICENSE.rst
MANIFEST.in
README.rst
casjobs.py
requirements.txt
setup.py
casjobs.egg-info/PKG-INFO
casjobs.egg-info/SOURCES.txt
casjobs.egg-info/dependency_links.txt
casjobs.egg-info/requires.txt
casjobs.egg-info/top_level.txt