Metadata-Version: 1.1
Name: casjobs
Version: 0.0.1
Summary: An interface to CasJobs for Humans.
Home-page: https://github.com/dfm/casjobs
Author: Daniel Foreman-Mackey
Author-email: danfm@nyu.edu
License: MIT
Platform: UNKNOWN
Classifier: Development Status :: 3 - Alpha
Classifier: Intended Audience :: Developers
Classifier: Intended Audience :: Science/Research
Classifier: License :: OSI Approved :: MIT License
Classifier: Operating System :: OS Independent
Classifier: Programming Language :: Python
